textprepro/__init__.py
textprepro/preprocess.py
textprepro/utils.py
textprepro-0.0.1.dist-info/LICENSE
textprepro-0.0.1.dist-info/METADATA
textprepro-0.0.1.dist-info/WHEEL
textprepro-0.0.1.dist-info/top_level.txt
textprepro-0.0.1.dist-info/RECORD
