Metadata-Version: 2.1
Name: textprepro
Version: 0.0.1
Summary: Everything Everyway All At Once Text Preprocessing.
Author-email: Umaporn Padungkiatwattana <umaploy@gmail.com>
License: MIT
Project-URL: Homepage, https://github.com/umapornp/textprepro
Project-URL: Documentation, https://github.com/umapornp/textprepro/blob/master/README.md
Project-URL: Source, https://github.com/umapornp/textprepro
Keywords: text preprocessing,text mining,NLP,Natural Language Processing
Classifier: Intended Audience :: Developers
Classifier: Intended Audience :: Education
Classifier: Intended Audience :: Science/Research
Classifier: License :: OSI Approved :: MIT License
Classifier: Programming Language :: Python :: 3
Classifier: Programming Language :: Python :: 3.8
Classifier: Programming Language :: Python :: 3.9
Classifier: Programming Language :: Python :: 3.10
Classifier: Programming Language :: Python :: 3.11
Classifier: Operating System :: OS Independent
Classifier: Topic :: Scientific/Engineering :: Artificial Intelligence
Classifier: Topic :: Text Processing
Requires-Python: >=3.8
License-File: LICENSE
Requires-Dist: beautifulsoup4
Requires-Dist: emoji
Requires-Dist: emot
Requires-Dist: gensim
Requires-Dist: scikit-learn
Requires-Dist: spacy
Requires-Dist: textblob
Requires-Dist: wordcloud
Requires-Dist: contractions
Requires-Dist: matplotlib
Requires-Dist: nltk
